lama2923/__init__.py
lama2923-2.0.7.dist-info/METADATA
lama2923-2.0.7.dist-info/WHEEL
lama2923-2.0.7.dist-info/top_level.txt
lama2923-2.0.7.dist-info/RECORD
