Metadata-Version: 2.2
Name: lama2923
Version: 2.0.7
Summary: Sikimsonik bir kütüphane
Author: lama2923
Author-email: lama2923.v2@gmail.com
Project-URL: Author GitHub, https://github.com/lama2923
Keywords: example project evelopment discord lama2923 api design custom custominput customprint
Classifier: Development Status :: 5 - Production/Stable
Classifier: Intended Audience :: Developers
Classifier: Programming Language :: Python :: 3
Classifier: Programming Language :: Python :: 3.7
Classifier: Programming Language :: Python :: 3.8
Classifier: Programming Language :: Python :: 3.9
Classifier: Programming Language :: Python :: 3.10
Classifier: Programming Language :: Python :: 3.11
Classifier: Operating System :: OS Independent
Requires-Python: >=3.7
Requires-Dist: colorama
Requires-Dist: requests
Requires-Dist: keyboard
Dynamic: author
Dynamic: author-email
Dynamic: classifier
Dynamic: description
Dynamic: description-content-type
Dynamic: keywords
Dynamic: project-url
Dynamic: requires-dist
Dynamic: requires-python
Dynamic: summary
